sprockets.clients.redis-1.0.1-py2.7-nspkg.pth
sprockets/clients/redis/__init__.py
sprockets.clients.redis-1.0.1.dist-info/namespace_packages.txt
sprockets.clients.redis-1.0.1.dist-info/top_level.txt
sprockets.clients.redis-1.0.1.dist-info/METADATA
sprockets.clients.redis-1.0.1.dist-info/DESCRIPTION.rst
sprockets.clients.redis-1.0.1.dist-info/metadata.json
sprockets.clients.redis-1.0.1.dist-info/WHEEL
sprockets.clients.redis-1.0.1.dist-info/RECORD
