Metadata-Version: 2.0
Name: sprockets.clients.redis
Version: 1.0.1
Summary: Base functionality for accessing/modifying data in Redis
Home-page: https://github.com/sprockets/sprockets.clients.redis.git
Author: AWeber Communications
Author-email: api@aweber.com
License: Copyright (c) 2014 AWeber Communications
Requires-Dist: consistent-hash (==1.0)
Requires-Dist: hiredis (==0.1.6)
Requires-Dist: redis (==2.10.3)
